LICENSE
MANIFEST.in
README.rst
setup.cfg
setup.py
versioneer.py
pymt_rafem/__init__.py
pymt_rafem/_version.py
pymt_rafem/bmi.py
pymt_rafem/rafem.py
pymt_rafem.egg-info/PKG-INFO
pymt_rafem.egg-info/SOURCES.txt
pymt_rafem.egg-info/dependency_links.txt
pymt_rafem.egg-info/entry_points.txt
pymt_rafem.egg-info/requires.txt
pymt_rafem.egg-info/top_level.txt
pymt_rafem/data/Rafem/api.yaml
pymt_rafem/data/Rafem/info.yaml
pymt_rafem/data/Rafem/input.yaml
pymt_rafem/data/Rafem/parameters.yaml
pymt_rafem/data/Rafem/run.yaml